{
    "lat":38.2629,
    "lon":-85.7031,
    "timezone":"America/Kentucky/Louisville",
    "timezone_offset":-14400,
    "current":{
       "dt":1647289819,
       "sunrise":1647258935,
       "sunset":1647301712,
       "temp":64.53,
       "feels_like":61.86,
       "pressure":1023,
       "humidity":25,
       "dew_point":28.44,
       "uvi":1.63,
       "clouds":0,
       "visibility":10000,
       "wind_speed":11.99,
       "wind_deg":176,
       "wind_gust":20,
       "weather":[
          {
             "id":800,
             "main":"Clear",
             "description":"clear sky",
             "icon":"01d"
          }
       ]
    },
    "daily":[
       {
          "dt":1647277200,
          "sunrise":1647258935,
          "sunset":1647301712,
          "moonrise":1647288420,
          "moonset":1647253020,
          "moon_phase":0.38,
          "temp":{
             "day":57.72,
             "min":37.56,
             "max":64.53,
             "night":49.41,
             "eve":61.45,
             "morn":37.92
          },
          "feels_like":{
             "day":54.93,
             "night":47.23,
             "eve":58.95,
             "morn":33.01
          },
          "pressure":1025,
          "humidity":37,
          "dew_point":31.69,
          "wind_speed":12.71,
          "wind_deg":203,
          "wind_gust":31.9,
          "weather":[
             {
                "id":803,
                "main":"Clouds",
                "description":"broken clouds",
                "icon":"04d"
             }
          ],
          "clouds":52,
          "pop":0,
          "uvi":4.54
       },
       {
          "dt":1647363600,
          "sunrise":1647345243,
          "sunset":1647388169,
          "moonrise":1647378660,
          "moonset":1647341580,
          "moon_phase":0.41,
          "temp":{
             "day":59.36,
             "min":45.68,
             "max":64.31,
             "night":54.09,
             "eve":61.72,
             "morn":46.18
          },
          "feels_like":{
             "day":56.97,
             "night":52.2,
             "eve":59.85,
             "morn":44.26
          },
          "pressure":1024,
          "humidity":42,
          "dew_point":36.28,
          "wind_speed":6.22,
          "wind_deg":206,
          "wind_gust":24.74,
          "weather":[
             {
                "id":804,
                "main":"Clouds",
                "description":"overcast clouds",
                "icon":"04d"
             }
          ],
          "clouds":100,
          "pop":0.04,
          "uvi":4.76
       },
       {
          "dt":1647450000,
          "sunrise":1647431550,
          "sunset":1647474626,
          "moonrise":1647468960,
          "moonset":1647429840,
          "moon_phase":0.44,
          "temp":{
             "day":62.89,
             "min":46.63,
             "max":66.04,
             "night":54.61,
             "eve":61.9,
             "morn":47.35
          },
          "feels_like":{
             "day":61.41,
             "night":53.62,
             "eve":60.6,
             "morn":45.9
          },
          "pressure":1017,
          "humidity":54,
          "dew_point":46.02,
          "wind_speed":6.93,
          "wind_deg":136,
          "wind_gust":13.09,
          "weather":[
             {
                "id":804,
                "main":"Clouds",
                "description":"overcast clouds",
                "icon":"04d"
             }
          ],
          "clouds":100,
          "pop":0,
          "uvi":4.88
       },
       {
          "dt":1647536400,
          "sunrise":1647517857,
          "sunset":1647561083,
          "moonrise":1647559320,
          "moonset":1647517860,
          "moon_phase":0.48,
          "temp":{
             "day":66.49,
             "min":49.69,
             "max":66.78,
             "night":58.64,
             "eve":62.2,
             "morn":50
          },
          "feels_like":{
             "day":65.52,
             "night":57.83,
             "eve":61.32,
             "morn":50
          },
          "pressure":1012,
          "humidity":57,
          "dew_point":50.86,
          "wind_speed":6.91,
          "wind_deg":196,
          "wind_gust":13.69,
          "weather":[
             {
                "id":803,
                "main":"Clouds",
                "description":"broken clouds",
                "icon":"04d"
             }
          ],
          "clouds":54,
          "pop":0,
          "uvi":4.88
       },
       {
          "dt":1647622800,
          "sunrise":1647604164,
          "sunset":1647647540,
          "moonrise":1647649740,
          "moonset":1647605820,
          "moon_phase":0.5,
          "temp":{
             "day":60.08,
             "min":43.34,
             "max":62.85,
             "night":43.34,
             "eve":45.93,
             "morn":56.57
          },
          "feels_like":{
             "day":59.68,
             "night":36.41,
             "eve":39.09,
             "morn":55.78
          },
          "pressure":1002,
          "humidity":83,
          "dew_point":54.77,
          "wind_speed":19.71,
          "wind_deg":226,
          "wind_gust":39.06,
          "weather":[
             {
                "id":500,
                "main":"Rain",
                "description":"light rain",
                "icon":"10d"
             }
          ],
          "clouds":89,
          "pop":1,
          "rain":4.14,
          "uvi":2.6
       },
       {
          "dt":1647709200,
          "sunrise":1647690471,
          "sunset":1647733996,
          "moonrise":1647740220,
          "moonset":1647693780,
          "moon_phase":0.55,
          "temp":{
             "day":54,
             "min":37.67,
             "max":57.79,
             "night":50.99,
             "eve":53.01,
             "morn":37.67
          },
          "feels_like":{
             "day":51.03,
             "night":48.76,
             "eve":50.63,
             "morn":31.17
          },
          "pressure":1020,
          "humidity":41,
          "dew_point":30.78,
          "wind_speed":13.44,
          "wind_deg":271,
          "wind_gust":25.52,
          "weather":[
             {
                "id":803,
                "main":"Clouds",
                "description":"broken clouds",
                "icon":"04d"
             }
          ],
          "clouds":60,
          "pop":0,
          "uvi":3
       },
       {
          "dt":1647795600,
          "sunrise":1647776777,
          "sunset":1647820452,
          "moonrise":1647830820,
          "moonset":1647781860,
          "moon_phase":0.58,
          "temp":{
             "day":63.39,
             "min":45.95,
             "max":66.51,
             "night":55.78,
             "eve":59.74,
             "morn":45.95
          },
          "feels_like":{
             "day":61.5,
             "night":54.07,
             "eve":57.99,
             "morn":42.4
          },
          "pressure":1024,
          "humidity":44,
          "dew_point":40.69,
          "wind_speed":9.33,
          "wind_deg":223,
          "wind_gust":31.81,
          "weather":[
             {
                "id":800,
                "main":"Clear",
                "description":"clear sky",
                "icon":"01d"
             }
          ],
          "clouds":2,
          "pop":0,
          "uvi":3
       },
       {
          "dt":1647882000,
          "sunrise":1647863084,
          "sunset":1647906909,
          "moonrise":1647921540,
          "moonset":1647870060,
          "moon_phase":0.62,
          "temp":{
             "day":66.22,
             "min":49.26,
             "max":67.89,
             "night":57.56,
             "eve":61.48,
             "morn":49.26
          },
          "feels_like":{
             "day":64.47,
             "night":55.89,
             "eve":59.92,
             "morn":48.49
          },
          "pressure":1026,
          "humidity":41,
          "dew_point":41.92,
          "wind_speed":9.42,
          "wind_deg":135,
          "wind_gust":23.62,
          "weather":[
             {
                "id":804,
                "main":"Clouds",
                "description":"overcast clouds",
                "icon":"04d"
             }
          ],
          "clouds":100,
          "pop":0,
          "uvi":3
       }
    ]
 }